cognite/datastudio/__init__.py
cognite/datastudio/client.py
cognite/datastudio/data_kit.py
cognite/datastudio/data_pipeline.py
cognite/datastudio/entity_extraction.py
cognite/datastudio/entity_matcher.py
cognite/datastudio/exceptions.py
cognite/datastudio/log.py
cognite/datastudio/pnid_parsing.py
cognite/datastudio/resource_typing.py
cognite/datastudio/rules.py
cognite/datastudio/utils.py
cognite_datastudio-0.4.1.dist-info/LICENSE
cognite_datastudio-0.4.1.dist-info/WHEEL
cognite_datastudio-0.4.1.dist-info/METADATA
cognite_datastudio-0.4.1.dist-info/RECORD
