Metadata-Version: 2.1
Name: cognite-datastudio
Version: 0.4.1
Summary: 
Author: cognite
Author-email: anders.hafreager@cognite.com
Requires-Python: >=3.6,<4.0
Classifier: Programming Language :: Python :: 3
Classifier: Programming Language :: Python :: 3.6
Classifier: Programming Language :: Python :: 3.7
Classifier: Programming Language :: Python :: 3.8
Requires-Dist: cognite-sdk (>=1.3,<2.0)
Requires-Dist: regex (>=2019.11,<2020.0)
Requires-Dist: typing_extensions (>=3.7,<4.0)
